{
  "$schema": "https://static.modelcontextprotocol.io/schemas/2025-07-09/server.schema.json",
  "name": "io.github.hbhqq9/bde-score",
  "description": "EU AI Act Art.50 compliant BDE stock scoring (US/HK/CN). Free, open-source.",
  "version": "1.0.2",
  "repository": {
    "url": "https://github.com/hbhqq9/bde-score",
    "source": "github",
    "id": "1295975285"
  },
  "website_url": "https://hbhqq9.github.io/bde-score/",
  "remotes": [
    {
      "type": "streamable-http",
      "url": "https://tex-adequate-date-facing.trycloudflare.com/mcp"
    }
  ],
  "tools": [
    {
      "name": "get_bde_score",
      "description": "Get BDE Score composite analysis (0-100) for a stock."
    },
    {
      "name": "get_stock_analysis",
      "description": "Get detailed BDE analysis for a specific stock."
    },
    {
      "name": "get_multi_market_comparison",
      "description": "Compare same company across US/HK/CN markets."
    },
    {
      "name": "get_stock_screener",
      "description": "Screen stocks by BDE score criteria."
    },
    {
      "name": "get_sector_analysis",
      "description": "Sector-level BDE analysis and rankings."
    },
    {
      "name": "get_esg_analysis",
      "description": "ESG analysis for a stock."
    }
  ]
}